gamblingandorangesconsolegames/__init__.py
gamblingandorangesconsolegames/ai/__init__.py
gamblingandorangesconsolegames/ai/ai_chat.py
gamblingandorangesconsolegames/calc/__init__.py
gamblingandorangesconsolegames/calc/calculator.py
gamblingandorangesconsolegames/fun/__init__.py
gamblingandorangesconsolegames/fun/asciiquarium.py
gamblingandorangesconsolegames/fun/pymatrix.py
gamblingandorangesconsolegames/games/__init__.py
gamblingandorangesconsolegames/games/checkers.py
gamblingandorangesconsolegames/games/chess.py
gamblingandorangesconsolegames/games/conways_game_of_life.py
gamblingandorangesconsolegames/games/pacman.py
gamblingandorangesconsolegames/games/snake.py
gamblingandorangesconsolegames/games/solitare.py
gamblingandorangesconsolegames/games/sudoku.py
gamblingandorangesconsolegames/games/tetris.py
gamblingandorangesconsolegames/games/tic_tac_toe.py
gamblingandorangesconsolegames/main.py
gamblingandorangesconsolegames/system_info.py
gamblingandorangesconsolegames-0.1.20.dist-info/LICENSE
gamblingandorangesconsolegames-0.1.20.dist-info/METADATA
gamblingandorangesconsolegames-0.1.20.dist-info/WHEEL
gamblingandorangesconsolegames-0.1.20.dist-info/entry_points.txt
gamblingandorangesconsolegames-0.1.20.dist-info/RECORD
