Metadata-Version: 2.1
Name: GamblingAndOrangesConsoleGames
Version: 0.1.20
Summary: a collection of terminal games written in python
Home-page: https://github.com/NoGambling1/ConsoleGames
License: MIT
Keywords: games,console,python,cli
Author: NoGambling
Requires-Python: >=3.12,<4.0
Classifier: Development Status :: 3 - Alpha
Classifier: Intended Audience :: Developers
Classifier: License :: OSI Approved :: MIT License
Classifier: Programming Language :: Python :: 3
Classifier: Programming Language :: Python :: 3.12
Requires-Dist: colorama (==0.4.6)
Requires-Dist: keyboard (==0.13.5)
Requires-Dist: psutil (>=6.0.0,<7.0.0)
Requires-Dist: pyperclip (>=1.9.0,<2.0.0)
Project-URL: Repository, https://github.com/NoGambling1/ConsoleGames
